dvq/__init__.py
dvq/statistical/KL_divergence.py
dvq/statistical/__init__.py
dvq/statistical/deng_entropy.py
dvq/statistical/kmer_representation.py
dvq/statistical/persistant_homology.py
dvq/statistical/wens_method.py
dvq/visual/__init__.py
dvq/visual/color_square.py
dvq/visual/representation_2d.py
dvq-0.0.4.8.5.dist-info/LICENSE
dvq-0.0.4.8.5.dist-info/METADATA
dvq-0.0.4.8.5.dist-info/WHEEL
dvq-0.0.4.8.5.dist-info/top_level.txt
dvq-0.0.4.8.5.dist-info/RECORD
