Metadata-Version: 2.2
Name: dvq
Version: 0.0.4.8.5
Summary: This is a library to validate and compare dna sequences
License: Apache-2.0
Requires-Python: >=3.8
License-File: LICENSE
Requires-Dist: numpy
Requires-Dist: matplotlib
Requires-Dist: persim
Requires-Dist: ripser
Requires-Dist: Cython
Requires-Dist: tqdm
Requires-Dist: sourmash
Provides-Extra: test
Requires-Dist: pytest; extra == "test"
